modelly_pdf/__init__.py
modelly_pdf/pdf.py
modelly_pdf-0.0.21.dist-info/METADATA
modelly_pdf-0.0.21.dist-info/WHEEL
modelly_pdf-0.0.21.dist-info/licenses/LICENSE
modelly_pdf-0.0.21.dist-info/RECORD
