Metadata-Version: 2.4
Name: modelly_pdf
Version: 0.0.21
Summary: Easily display PDFs in Modelly
Author-email: Md Sulaiman <dev.sulaiman@icloud.com>
License-Expression: Apache-2.0
License-File: LICENSE
Keywords: Document QA,Documents,PDF,modelly,modelly custom component,modelly-template-Fallback
Classifier: Development Status :: 3 - Alpha
Classifier: License :: OSI Approved :: Apache Software License
Classifier: Operating System :: OS Independent
Classifier: Programming Language :: Python :: 3
Classifier: Programming Language :: Python :: 3 :: Only
Classifier: Programming Language :: Python :: 3.8
Classifier: Programming Language :: Python :: 3.9
Classifier: Programming Language :: Python :: 3.10
Classifier: Programming Language :: Python :: 3.11
Classifier: Topic :: Scientific/Engineering
Classifier: Topic :: Scientific/Engineering :: Artificial Intelligence
Classifier: Topic :: Scientific/Engineering :: Visualization
Requires-Python: >=3.8
Requires-Dist: modelly<6.0,>=1.0
Provides-Extra: dev
Requires-Dist: build; extra == 'dev'
Requires-Dist: twine; extra == 'dev'
